mcp_seniverse_weather_mqslllddyy_1/__init__.py
mcp_seniverse_weather_mqslllddyy_1/__main__.py
mcp_seniverse_weather_mqslllddyy_1/server.py
mcp_seniverse_weather_mqslllddyy_1-1.0.0.dist-info/METADATA
mcp_seniverse_weather_mqslllddyy_1-1.0.0.dist-info/WHEEL
mcp_seniverse_weather_mqslllddyy_1-1.0.0.dist-info/entry_points.txt
mcp_seniverse_weather_mqslllddyy_1-1.0.0.dist-info/RECORD
