Metadata-Version: 2.4
Name: mcp-seniverse-weather-mqslllddyy-1
Version: 1.0.0
Summary: Weather Forecast MCP Server Powered by Seniverse
Requires-Python: >=3.13
Requires-Dist: httpx>=0.28.1
Requires-Dist: mcp[cli]>=1.9.4
Requires-Dist: requests>=2.32.4
